MANIFEST.in
README.md
requirements.txt
setup.cfg
setup.py
termagotchi/__init__.py
termagotchi.egg-info/PKG-INFO
termagotchi.egg-info/SOURCES.txt
termagotchi.egg-info/dependency_links.txt
termagotchi.egg-info/requires.txt
termagotchi.egg-info/top_level.txt